pywbt/__init__.py
pywbt/cli.py
pywbt/dem_utils.py
pywbt/py.typed
pywbt/pywbt.py
pywbt-0.3.0.dist-info/METADATA
pywbt-0.3.0.dist-info/WHEEL
pywbt-0.3.0.dist-info/entry_points.txt
pywbt-0.3.0.dist-info/licenses/AUTHORS.md
pywbt-0.3.0.dist-info/licenses/LICENSE
pywbt-0.3.0.dist-info/RECORD
