Metadata-Version: 2.4
Name: pywbt
Version: 0.3.0
Summary: A lightweight Python wrapper for WhiteboxTools command-line interface
Project-URL: Changelog, https://github.com/cheginit/pywbt/blob/main/CHANGELOG.md
Project-URL: CI, https://github.com/cheginit/pywbt/actions
Project-URL: Homepage, https://github.com/cheginit/pywbt
Project-URL: Issues, https://github.com/cheginit/pywbt/issues
Author-email: Taher Chegini <cheginit@gmail.com>
License: MIT
License-File: AUTHORS.md
License-File: LICENSE
Classifier: Development Status :: 4 - Beta
Classifier: Intended Audience :: Science/Research
Classifier: License :: OSI Approved :: MIT License
Classifier: Operating System :: OS Independent
Classifier: Programming Language :: Python
Classifier: Programming Language :: Python :: 3 :: Only
Classifier: Programming Language :: Python :: 3.10
Classifier: Programming Language :: Python :: 3.11
Classifier: Programming Language :: Python :: 3.12
Classifier: Programming Language :: Python :: 3.13
Classifier: Topic :: Scientific/Engineering
Classifier: Topic :: Scientific/Engineering :: GIS
Classifier: Topic :: Scientific/Engineering :: Hydrology
Classifier: Typing :: Typed
Requires-Python: >=3.10
Requires-Dist: filelock
Provides-Extra: cli
Requires-Dist: tomli>=1.1; (python_version < '3.11') and extra == 'cli'
Provides-Extra: dem
Requires-Dist: geopandas>=1; extra == 'dem'
Requires-Dist: planetary-computer; extra == 'dem'
Requires-Dist: pystac-client; extra == 'dem'
Requires-Dist: rioxarray; extra == 'dem'
Requires-Dist: seamless-3dep>=0.3.1; extra == 'dem'
Requires-Dist: tiny-retriever>=0.1.2; extra == 'dem'
Provides-Extra: dev
Requires-Dist: folium; extra == 'dev'
Requires-Dist: geopandas>=1; extra == 'dev'
Requires-Dist: ipykernel; extra == 'dev'
Requires-Dist: ipywidgets; extra == 'dev'
Requires-Dist: mapclassify; extra == 'dev'
Requires-Dist: matplotlib; extra == 'dev'
Requires-Dist: planetary-computer; extra == 'dev'
Requires-Dist: pystac-client; extra == 'dev'
Requires-Dist: pytest; extra == 'dev'
Requires-Dist: rioxarray; extra == 'dev'
Requires-Dist: seamless-3dep>=0.3.1; extra == 'dev'
Requires-Dist: tiny-retriever>=0.1.2; extra == 'dev'
Requires-Dist: tomli>=1.1; (python_version < '3.11') and extra == 'dev'
Provides-Extra: docs
Requires-Dist: black; extra == 'docs'
Requires-Dist: mkdocs-jupyter; extra == 'docs'
Requires-Dist: mkdocs-macros-plugin; extra == 'docs'
Requires-Dist: mkdocs-material>=9.5.20; extra == 'docs'
Requires-Dist: mkdocs>=1.5.3; extra == 'docs'
Requires-Dist: mkdocstrings-python; extra == 'docs'
Provides-Extra: lint
Requires-Dist: codespell; extra == 'lint'
Requires-Dist: pre-commit; extra == 'lint'
Provides-Extra: test
Requires-Dist: coverage[toml]; extra == 'test'
Requires-Dist: pytest; extra == 'test'
Requires-Dist: pytest-cov; extra == 'test'
Requires-Dist: pytest-sugar; extra == 'test'
Provides-Extra: typecheck
Requires-Dist: pyright; extra == 'typecheck'
